costmodels/__init__.py
costmodels/_version.py
costmodels/cmodel.py
costmodels/finance.py
costmodels/project.py
costmodels/models/__init__.py
costmodels/models/battery_cost.py
costmodels/models/dtu_offshore.py
costmodels/models/minimalistic.py
costmodels/models/nrel.py
costmodels/models/p2h2_cost.py
costmodels/models/pv.py
costmodels/models/shared_cost.py
costmodels/models/external/nrel_csm_cost_2015.py
costmodels/models/external/nrel_csm_mass_2015.py
costmodels-0.2.1.dist-info/METADATA
costmodels-0.2.1.dist-info/WHEEL
costmodels-0.2.1.dist-info/RECORD
