Metadata-Version: 2.4
Name: costmodels
Version: 0.2.1
Summary: Add a short description here
Author-email: ernie <ernim@dtu.dk>
Requires-Python: <3.13,>=3.10
Requires-Dist: jax<1.0,>=0.5.3
Requires-Dist: matplotlib<4,>=3.7.5
Requires-Dist: numpy
Requires-Dist: scipy<2,>=1.10.1
Provides-Extra: test
Requires-Dist: mypy<2,>=1.18.2; extra == 'test'
Requires-Dist: openmdao<4,>=3.36.0; extra == 'test'
Requires-Dist: pandas<3,>=2.2.3; extra == 'test'
Requires-Dist: pre-commit<5,>=4.1.0; extra == 'test'
Requires-Dist: psutil<8,>=7.0.0; extra == 'test'
Requires-Dist: pytest-cov<7,>=6.0.0; extra == 'test'
Requires-Dist: pytest-xdist<4,>=3.6.1; extra == 'test'
Requires-Dist: pytest<9,>=8.3.4; extra == 'test'
